edc_review_dashboard/__init__.py
edc_review_dashboard/apps.py
edc_review_dashboard/auths.py
edc_review_dashboard/dashboard_templates.py
edc_review_dashboard/middleware.py
edc_review_dashboard/models.py
edc_review_dashboard/navbars.py
edc_review_dashboard/system_checks.py
edc_review_dashboard/urls.py
edc_review_dashboard/locale/sw/LC_MESSAGES/django.mo
edc_review_dashboard/locale/sw/LC_MESSAGES/django.po
edc_review_dashboard/migrations/0001_initial.py
edc_review_dashboard/migrations/0002_auto_20220825_0451.py
edc_review_dashboard/migrations/0003_alter_edcpermissions_device_created_and_more.py
edc_review_dashboard/migrations/0004_edcpermissions_locale_created_and_more.py
edc_review_dashboard/migrations/__init__.py
edc_review_dashboard/templates/edc_review_dashboard/home.html
edc_review_dashboard/templates/edc_review_dashboard/subject_review_button.html
edc_review_dashboard/templates/edc_review_dashboard/subject_review_listboard.html
edc_review_dashboard/tests/__init__.py
edc_review_dashboard/tests/holidays.csv
edc_review_dashboard/tests/test_settings.py
edc_review_dashboard/tests/urls.py
edc_review_dashboard/tests/etc/user-aes-local.key
edc_review_dashboard/tests/etc/user-aes-restricted.key
edc_review_dashboard/tests/etc/user-rsa-local-private.pem
edc_review_dashboard/tests/etc/user-rsa-local-public.pem
edc_review_dashboard/tests/etc/user-rsa-restricted-private.pem
edc_review_dashboard/tests/etc/user-rsa-restricted-public.pem
edc_review_dashboard/tests/etc/user-salt-local.key
edc_review_dashboard/tests/etc/user-salt-restricted.key
edc_review_dashboard/tests/tests/__init__.py
edc_review_dashboard/tests/tests/test_dashboard.py
edc_review_dashboard/views/__init__.py
edc_review_dashboard/views/subject_review_listboard_view.py
edc_review_dashboard-1.0.2.dist-info/licenses/AUTHORS.rst
edc_review_dashboard-1.0.2.dist-info/licenses/LICENSE
review_dashboard_app/__init__.py
review_dashboard_app/admin.py
review_dashboard_app/admin_site.py
review_dashboard_app/apps.py
review_dashboard_app/consents.py
review_dashboard_app/lab_profiles.py
review_dashboard_app/models.py
edc_review_dashboard-1.0.2.dist-info/METADATA
edc_review_dashboard-1.0.2.dist-info/WHEEL
edc_review_dashboard-1.0.2.dist-info/top_level.txt
edc_review_dashboard-1.0.2.dist-info/RECORD
